binance_sdk_derivatives_trading_portfolio_margin_pro/__init__.py
binance_sdk_derivatives_trading_portfolio_margin_pro/derivatives_trading_portfolio_margin_pro.py
binance_sdk_derivatives_trading_portfolio_margin_pro/metadata.py
binance_sdk_derivatives_trading_portfolio_margin_pro/rest_api/__init__.py
binance_sdk_derivatives_trading_portfolio_margin_pro/rest_api/api/__init__.py
binance_sdk_derivatives_trading_portfolio_margin_pro/rest_api/api/account_api.py
binance_sdk_derivatives_trading_portfolio_margin_pro/rest_api/api/market_data_api.py
binance_sdk_derivatives_trading_portfolio_margin_pro/rest_api/models/__init__.py
binance_sdk_derivatives_trading_portfolio_margin_pro/rest_api/models/bnb_transfer_response.py
binance_sdk_derivatives_trading_portfolio_margin_pro/rest_api/models/change_auto_repay_futures_status_response.py
binance_sdk_derivatives_trading_portfolio_margin_pro/rest_api/models/enums.py
binance_sdk_derivatives_trading_portfolio_margin_pro/rest_api/models/fund_auto_collection_response.py
binance_sdk_derivatives_trading_portfolio_margin_pro/rest_api/models/fund_collection_by_asset_response.py
binance_sdk_derivatives_trading_portfolio_margin_pro/rest_api/models/get_auto_repay_futures_status_response.py
binance_sdk_derivatives_trading_portfolio_margin_pro/rest_api/models/get_delta_mode_status_response.py
binance_sdk_derivatives_trading_portfolio_margin_pro/rest_api/models/get_portfolio_margin_asset_leverage_response.py
binance_sdk_derivatives_trading_portfolio_margin_pro/rest_api/models/get_portfolio_margin_asset_leverage_response_inner.py
binance_sdk_derivatives_trading_portfolio_margin_pro/rest_api/models/get_portfolio_margin_pro_account_balance_response.py
binance_sdk_derivatives_trading_portfolio_margin_pro/rest_api/models/get_portfolio_margin_pro_account_balance_response_inner.py
binance_sdk_derivatives_trading_portfolio_margin_pro/rest_api/models/get_portfolio_margin_pro_account_info_response.py
binance_sdk_derivatives_trading_portfolio_margin_pro-5.3.0.dist-info/METADATA
binance_sdk_derivatives_trading_portfolio_margin_pro-5.3.0.dist-info/WHEEL
binance_sdk_derivatives_trading_portfolio_margin_pro-5.3.0.dist-info/licenses/LICENCE
binance_sdk_derivatives_trading_portfolio_margin_pro-5.3.0.dist-info/RECORD
